modfetch/__init__.py
modfetch/__main__.py
modfetch/api.py
modfetch/core.py
modfetch/error.py
modfetch-0.1.1.dist-info/METADATA
modfetch-0.1.1.dist-info/WHEEL
modfetch-0.1.1.dist-info/entry_points.txt
modfetch-0.1.1.dist-info/top_level.txt
modfetch-0.1.1.dist-info/RECORD
