Metadata-Version: 2.4
Name: modfetch
Version: 0.1.1
Summary: Add your description here
Requires-Python: >=3.9
Requires-Dist: aiofiles>=24.1.0
Requires-Dist: aiohttp>=3.12.15
Requires-Dist: click>=8.2.1
Requires-Dist: pyyaml>=6.0.2
Requires-Dist: toml>=0.10.2
Requires-Dist: xmltodict>=0.14.2
